[
  {
    "username": "arthur",
    "password": "123",
    "balance": 0.0,
    "goals": [],
    "transactions": [
      {
        "name": "johnny",
        "amount": -20.0,
        "description": "spoil yourself",
        "dateString": "2025-03-11T10:48:34.207815900"
      },
      {
        "name": "johnny",
        "amount": 20.0,
        "description": "have it back",
        "dateString": "2025-03-11T10:51:35.970571800"
      }
    ]
  },
  {
    "username": "johnny",
    "password": "456",
    "balance": 0.0,
    "goals": [],
    "transactions": [
      {
        "name": "arthur",
        "amount": 20.0,
        "description": "spoil yourself",
        "dateString": "2025-03-11T10:48:34.206307500"
      },
      {
        "name": "arthur",
        "amount": -20.0,
        "description": "have it back",
        "dateString": "2025-03-11T10:51:35.971203900"
      }
    ]
  }
]